{
  "$schema": "./node_modules/@biomejs/biome/configuration_schema.json",
  "files": {
    "ignoreUnknown": false,
    "ignore": []
  },
  "formatter": {
    "enabled": true,
    "indentStyle": "space",
    "indentWidth": 2
  },
  "organizeImports": {
    "enabled": true
  },
  "linter": {
    "enabled": true,
    "rules": {
      "recommended": true,
      "nursery": { "useSortedClasses": "warn" },
      "correctness": {
        "noUnusedImports": "warn",
        "noUnusedVariables": "warn"
      }
    }
  },
  "css": {
    "formatter": {
      "enabled": true,
      "indentStyle": "space",
      "indentWidth": 2
    },
    "linter": {
      "enabled": true
    },
    "parser": {
      "cssModules": true
    }
  },
  "vcs": {
    "enabled": false,
    "clientKind": "git",
    "useIgnoreFile": false
  },
  "javascript": {
    "formatter": {
      "quoteStyle": "double"
    }
  }
}
